{
    "total": 161,
    "dispositivos": {
        "Celular / Smartphone": 110,
        "Tablet": 66,
        "Laptop": 65,
        "Computadora de escritorio": 48,
        "Consola de videojuegos": 45,
        "Televisión": 6,
        "Ninguno": 1
    },
    "horas": {
        "1 a 2 horas": 64,
        "3 a 4 horas": 35,
        "5 horas o más": 35,
        "Menos de 1 hora": 27
    },
    "uso": {
        "Jugar": 137,
        "Ver videos": 114,
        "Hacer tareas": 98,
        "Aprender cosas nuevas": 62,
        "Redes sociales": 35
    },
    "estudio": {
        "A veces": 111,
        "Siempre": 23,
        "Casi nunca": 20,
        "Nunca": 7
    },
    "redes": {
        "YouTube": 147,
        "WhatsApp": 72,
        "TikTok": 63,
        "Instagram": 16,
        "Facebook": 16,
        "Roblox": 12,
        "Ninguno": 1
    },
    "horas_redes": {
        "1 a 2 horas": 61,
        "Menos de 1 hora": 56,
        "3 a 4 horas": 25,
        "5 horas o más": 19
    },
    "uso_redes": {
        "Ver videos": 127,
        "Entretenimiento": 99,
        "Hablar con amigos": 84,
        "Aprender cosas nuevas": 61,
        "Compartir fotos": 25
    }
}